langspeak.py
javaspeak/__init__.py
javaspeak/javaspeak.py
pythonspeak/__init__.py
pythonspeak/pythonspeak.py
rustspeak/__init__.py
rustspeak/rustspeak.py
szp_project-0.0.1.dist-info/METADATA
szp_project-0.0.1.dist-info/WHEEL
szp_project-0.0.1.dist-info/top_level.txt
szp_project-0.0.1.dist-info/RECORD
